xo/__init__.py
xo/ai.py
xo/ai_core.py
xo/cache_system.py
xo/cli.py
xo/database.py
xo/find_matches.py
xo/memory_system.py
xo/response_engine.py
xo_ai-1.0.0.dist-info/licenses/LICENSE
xo_ai-1.0.0.dist-info/METADATA
xo_ai-1.0.0.dist-info/WHEEL
xo_ai-1.0.0.dist-info/entry_points.txt
xo_ai-1.0.0.dist-info/top_level.txt
xo_ai-1.0.0.dist-info/RECORD
