Metadata-Version: 2.4
Name: xo-ai
Version: 1.0.0
Summary: XO — Minimal Conversational Intelligence Framework with Memory and Reinforcement
Author: XO Aria
Author-email: XO Aria <hf18950@gmail.com>
License: MIT
Project-URL: Homepage, https://github.com/xo-aria/xo-ai
Project-URL: Repository, https://github.com/xo-aria/xo-ai
Project-URL: Documentation, https://github.com/xo-aria/xo-ai/wiki
Project-URL: Issues, https://github.com/xo-aria/xo-ai/issues
Classifier: Development Status :: 5 - Production/Stable
Classifier: Intended Audience :: Developers
Classifier: Topic :: Scientific/Engineering :: Artificial Intelligence
Classifier: Topic :: Communications :: Chat
Classifier: License :: OSI Approved :: MIT License
Classifier: Programming Language :: Python :: 3
Classifier: Programming Language :: Python :: 3.8
Classifier: Programming Language :: Python :: 3.9
Classifier: Programming Language :: Python :: 3.10
Classifier: Programming Language :: Python :: 3.11
Classifier: Operating System :: OS Independent
Requires-Python: >=3.8
License-File: LICENSE
Dynamic: author
Dynamic: license-file
Dynamic: requires-python
